{"productId":10448,"sku":"SKE-15460","name":"Across The Pond Boots","productUrl":"https:\/\/www.domain.com\/product\/ske-15460","price":74.49,"retailPrice":74.49,"thumbnailUrl":"https:\/\/www.domain.com\/images\/ske-15460_600x600.png","searchKeywords":"lorem, ipsum, dolor, ...","description":"Sociosqu facilisis duis ...","category":"Shoes>Boots>Flat Boots","categoryId":334,"brand":"Legacy Collective","childSku":"SKE-15460-BRN-6|SKE-15460-BRN-7|SKE-15460-BRN-8.5","childPrice":"","color":"Brown","colorFamily":"Brown","colorSwatches":"","size":"","shoeSize":"6|7|8.5","pantsSize":"","occassion":"","season":"","badges":"","ratingAvg":5,"ratingCount":6,"inventoryCount":0,"dateCreated":"2018-06-25 18:09:07","viewed":1,"frequentlyAdded":1,"_id":58}